gammalearn/__init__.py
gammalearn/_version.py
gammalearn/experiment_paths.py
gammalearn/experiment_runner.py
gammalearn/gammalearn_lightning_module.py
gammalearn/optimizers.py
gammalearn/training_steps.py
gammalearn/configuration/__init__.py
gammalearn/configuration/constants.py
gammalearn/configuration/dataloading.py
gammalearn/configuration/dataset.py
gammalearn/configuration/gl_logging.py
gammalearn/configuration/save_configuration.py
gammalearn/configuration/examples/config_train_MC.yaml
gammalearn/configuration/examples/experiment_settings_adistance.py
gammalearn/configuration/examples/experiment_settings_autoencoder.py
gammalearn/configuration/examples/experiment_settings_cbn.py
gammalearn/configuration/examples/experiment_settings_clean_channel.py
gammalearn/configuration/examples/experiment_settings_dann.py
gammalearn/configuration/examples/experiment_settings_digits.py
gammalearn/configuration/examples/experiment_settings_file_spawn.py
gammalearn/configuration/examples/experiment_settings_fine_tuning.py
gammalearn/configuration/examples/experiment_settings_gammaphysnet.py
gammalearn/configuration/examples/experiment_settings_gammaphysnet_indexed.py
gammalearn/configuration/examples/experiment_settings_gradnorm.py
gammalearn/configuration/examples/experiment_settings_mae_image.py
gammalearn/configuration/examples/experiment_settings_mae_lst.py
gammalearn/configuration/examples/experiment_settings_megatron.py
gammalearn/configuration/examples/experiment_settings_prime.py
gammalearn/configuration/examples/experiment_settings_profiler.py
gammalearn/configuration/examples/experiment_settings_test_MC.py
gammalearn/configuration/examples/experiment_settings_test_real.py
gammalearn/configuration/examples/experiment_settings_train_MC.py
gammalearn/configuration/examples/experiment_settings_val.py
gammalearn/criterion/DANN_loss.py
gammalearn/criterion/__init__.py
gammalearn/criterion/multitask.py
gammalearn/criterion/utils.py
gammalearn-0.15.0.dist-info/licenses/LICENSE
gammalearn-0.15.0.dist-info/METADATA
gammalearn-0.15.0.dist-info/WHEEL
gammalearn-0.15.0.dist-info/entry_points.txt
gammalearn-0.15.0.dist-info/top_level.txt
gammalearn-0.15.0.dist-info/RECORD
