Metadata-Version: 2.4
Name: gammalearn
Version: 0.15.0
Summary: A framework to easily train deep learning model on Imaging Atmospheric Cherenkov Telescopes data
Author-email: "M. Jacquemont" <jacquemont@lapp.in2p3.fr>, "T. Vuillaume" <thomas.vuillaume@lapp.in2p3.fr>
License: MIT License
Project-URL: Homepage, https://gammalearn.pages.in2p3.fr/pages/
Project-URL: Repository, https://gitlab.in2p3.fr/gammalearn/gammalearn
Project-URL: Documentation, https://gammalearn.pages.in2p3.fr/gammalearn/
Project-URL: Bug Tracker, https://gitlab.in2p3.fr/gammalearn/gammalearn/-/issues
Classifier: Programming Language :: Python :: 3
Classifier: License :: OSI Approved :: MIT License
Classifier: Operating System :: OS Independent
Requires-Python: >=3.11
License-File: LICENSE
Requires-Dist: astropy
Requires-Dist: ctapipe
Requires-Dist: ctaplot
Requires-Dist: dl1_data_handler
Requires-Dist: h5py
Requires-Dist: indexedconv
Requires-Dist: lightning
Requires-Dist: lstchain
Requires-Dist: matplotlib
Requires-Dist: numpy
Requires-Dist: pandas
Requires-Dist: pillow
Requires-Dist: tables
Requires-Dist: pot
Requires-Dist: pytorch
Requires-Dist: scikit-image
Requires-Dist: setuptools
Requires-Dist: tensorboardX
Requires-Dist: torchaudio
Requires-Dist: torchmetrics
Requires-Dist: torchvision
Requires-Dist: tqdm
Requires-Dist: wandb
Provides-Extra: tests
Requires-Dist: myst-parser; extra == "tests"
Requires-Dist: numpydoc; extra == "tests"
Requires-Dist: pytest; extra == "tests"
Requires-Dist: pytest-cov; extra == "tests"
Requires-Dist: recommonmark; extra == "tests"
Requires-Dist: ruff; extra == "tests"
Requires-Dist: sphinx; extra == "tests"
Requires-Dist: sphinx_rtd_theme; extra == "tests"
Requires-Dist: sphinx-argparse; extra == "tests"
Requires-Dist: sphinx-multiversion; extra == "tests"
Requires-Dist: nbsphinx; extra == "tests"
Dynamic: license-file
